README.md
setup.py
spatial/__init__.py
spatial/bounds.py
spatial.egg-info/PKG-INFO
spatial.egg-info/SOURCES.txt
spatial.egg-info/dependency_links.txt
spatial.egg-info/top_level.txt