Metadata-Version: 2.1
Name: spatial
Version: 0.1.0
Summary: A small pure python library for spatial queries, functions and classes
Home-page: https://github.com/mikemalinowski/spatial
Author: Mike Malinowski
Author-email: mike@twisted.space
License: UNKNOWN
Platform: UNKNOWN
Classifier: Programming Language :: Python
Classifier: License :: OSI Approved :: MIT License
Classifier: Operating System :: OS Independent
